fastbm25/__init__.py
fastbm25/fastbm25.py
fastbm25-0.0.2.dist-info/LICENSE
fastbm25-0.0.2.dist-info/METADATA
fastbm25-0.0.2.dist-info/WHEEL
fastbm25-0.0.2.dist-info/top_level.txt
fastbm25-0.0.2.dist-info/RECORD
