Metadata-Version: 2.1
Name: fastbm25
Version: 0.0.2
Summary: Fast text match algorithm implementation for bm25
Home-page: https://github.com/zhusleep/fastbm25
Author: zhusleep
Author-email: zhuflower@qq.com
Classifier: Programming Language :: Python :: 3
Classifier: License :: OSI Approved :: MIT License
Classifier: Operating System :: OS Independent
Requires-Python: >=3.5
License-File: LICENSE
